client/__init__.py
client/client.py
client/client_pack/__init__.py
client/client_pack/add_contact.py
client/client_pack/database.py
client/client_pack/del_contact.py
client/client_pack/main_window.py
client/client_pack/main_window_conv.py
client/client_pack/start_dialog.py
client/client_pack/transport.py
client/common/__init__.py
client/common/decors.py
client/common/descripts.py
client/common/errors.py
client/common/metaclasses.py
client/common/utils.py
client/common/variables.py
client/logs/__init__.py
client/logs/client_logs/__init__.py
client/logs/configs/__init__.py
client/logs/configs/client_log_config.py
client/logs/configs/server_log_config.py
client/logs/server_logs/__init__.py
client/unit_test/__init__.py
client/unit_test/test_client.py
client/unit_test/test_server.py
client/unit_test/test_utils.py
my_py_mess_client-0.0.1.dist-info/METADATA
my_py_mess_client-0.0.1.dist-info/WHEEL
my_py_mess_client-0.0.1.dist-info/top_level.txt
my_py_mess_client-0.0.1.dist-info/RECORD
